Metadata-Version: 2.1
Name: pywinforms
Version: 0.0.1
Summary: A python library to create Windows Forms applications
Home-page: https://github.com/danielnachumdev/pywinforms
Author: danielnachumdev
Author-email: danielnachumdev <danielnachumdev@gmail.com>
License: MIT License
Project-URL: Homepage, https://github.com/danielnachumdev/pywinforms
Project-URL: Bug Tracker, https://github.com/danielnachumdev/pywinforms/issues
Keywords: C#,dontnet,Windows Froms,classes
Platform: All
Classifier: Development Status :: 3 - Alpha
Classifier: Intended Audience :: Developers
Classifier: Programming Language :: Python :: 3
Classifier: Operating System :: Microsoft :: Windows
Requires-Python: >=3.11.3
License-File: LICENSE
Requires-Dist: danielutils
